pytreelib/__init__.py
pytreelib/node.py
pytreelib/tree.py
pytreelib-0.1.1.dist-info/LICENSE
pytreelib-0.1.1.dist-info/METADATA
pytreelib-0.1.1.dist-info/WHEEL
pytreelib-0.1.1.dist-info/top_level.txt
pytreelib-0.1.1.dist-info/RECORD
