Metadata-Version: 2.1
Name: pytreelib
Version: 0.1.1
Summary: Simple Binary Tree Data Structure Implementation
Home-page: https://github.com/akashbw/pytreelib
Author: Akash Jain
Author-email: akashjain0108@gmail.com
License: MIT
Keywords: data structure,tree,binary tree
Platform: UNKNOWN
